widely/__init__.py
widely/bucket.py
widely/diff.py
widely/util.py
widely/commands/__init__.py
widely/commands/auth.py
widely/commands/domains.py
widely/commands/help.py
widely/commands/local.py
widely/commands/logs.py
widely/commands/open.py
widely/commands/pull.py
widely/commands/push.py
widely/commands/sites.py
widely/commands/status.py
widely/commands/version.py
widely-0.16.dist-info/DESCRIPTION.rst
widely-0.16.dist-info/METADATA
widely-0.16.dist-info/RECORD
widely-0.16.dist-info/WHEEL
widely-0.16.dist-info/entry_points.txt
widely-0.16.dist-info/metadata.json
widely-0.16.dist-info/top_level.txt
