Metadata-Version: 2.0
Name: widely
Version: 0.16
Summary: Static Site as a Service using AWS S3
Home-page: http://www.celador.mn/widely
Author: Kyle Marek-Spartz and Michael Burling
Author-email: kyle.marek.spartz@gmail.com
License: MIT
Platform: UNKNOWN
Classifier: Development Status :: 3 - Alpha
Classifier: Environment :: Console
Classifier: Intended Audience :: Developers
Classifier: Intended Audience :: Information Technology
Classifier: Intended Audience :: System Administrators
Classifier: License :: OSI Approved :: MIT License
Classifier: Programming Language :: Python :: 2.7
Classifier: Programming Language :: Python :: 2 :: Only
Classifier: Topic :: Internet
Classifier: Topic :: Internet :: WWW/HTTP
Classifier: Topic :: Internet :: WWW/HTTP :: Site Management
Classifier: Topic :: Utilities
Requires-Dist: boto (==2.22.1)
Requires-Dist: docopt (==0.6.1)
Requires-Dist: feedparser (==5.1.3)
Requires-Dist: prettytable (==0.7.2)
